bih.cpython-37m-x86_64-linux-gnu.so
bih-1.0.2.dist-info/top_level.txt
bih-1.0.2.dist-info/WHEEL
bih-1.0.2.dist-info/LICENSE
bih-1.0.2.dist-info/METADATA
bih-1.0.2.dist-info/RECORD
