Metadata-Version: 2.1
Name: bih
Version: 1.0.2
Summary: Bounded Interval Hierarchy.
Home-page: https://github.com/flow123d/bih
Author: Jan Brezina
Author-email: jan.brezina@tul.cz
License: GPL 3.0
Platform: UNKNOWN
Classifier: License :: OSI Approved :: GNU General Public License v3 or later (GPLv3+)
Classifier: Operating System :: Unix
Classifier: Operating System :: POSIX
Classifier: Operating System :: Microsoft :: Windows
Classifier: Programming Language :: Python :: 3
Classifier: Topic :: Scientific/Engineering
Requires-Python: >=3
License-File: LICENSE
Requires-Dist: numpy (>=1.13.4)
